maws/__init__.py
maws/clients/.gitignore
maws/clients/.ruff_cache/.gitignore
maws/clients/.ruff_cache/0.12.8/1767651899173820239
maws/clients/.ruff_cache/CACHEDIR.TAG
maws/clients/README.md
maws/clients/ecs_service_deployment_client/__init__.py
maws/clients/ecs_service_deployment_client/api/__init__.py
maws/clients/ecs_service_deployment_client/api/services/__init__.py
maws/clients/ecs_service_deployment_client/api/services/get_service.py
maws/clients/ecs_service_deployment_client/api/services/get_services.py
maws/clients/ecs_service_deployment_client/api/services/patch_service.py
maws/clients/ecs_service_deployment_client/api/tasks/__init__.py
maws/clients/ecs_service_deployment_client/api/tasks/get_tasks.py
maws/clients/ecs_service_deployment_client/api/tasks/patch_task.py
maws/clients/ecs_service_deployment_client/client.py
maws/clients/ecs_service_deployment_client/errors.py
maws/clients/ecs_service_deployment_client/models/__init__.py
maws/clients/ecs_service_deployment_client/models/error_response.py
maws/clients/ecs_service_deployment_client/models/service_deployment_request.py
maws/clients/ecs_service_deployment_client/models/task_deployment_request.py
maws/clients/ecs_service_deployment_client/py.typed
maws/clients/ecs_service_deployment_client/types.py
maws/clients/pyproject.toml
maws/commands/ecs.py
maws/config.py
maws/main.py
maws-25.12.2.dist-info/WHEEL
maws-25.12.2.dist-info/entry_points.txt
maws-25.12.2.dist-info/METADATA
maws-25.12.2.dist-info/RECORD
