Metadata-Version: 2.3
Name: maws
Version: 25.12.2
Summary: Managed AWS command line client
Author: Jochen Werner, Stefan Heitmüller
Author-email: Jochen Werner <jochen.werner@skaylink.com>, Stefan Heitmüller <stefan.heitmueller@skaylink.com>
Requires-Dist: pydantic==2.11.4
Requires-Dist: pydantic-settings==2.9.1
Requires-Dist: typer==0.15.4
Requires-Dist: rich==14.0.0
Requires-Dist: openapi-python-client>=0.25.3
Requires-Dist: mypy-extensions>=1.1.0
Requires-Dist: pathspec>=0.12.1
Requires-Python: >=3.12
Project-URL: Repository, https://github.com/skaylink/maws
